docstring_checker/__init__.py
docstring_checker/doc_node.py
docstring_checker/docstring_checker_base_exception.py
docstring_checker/error_printer_from_file.py
docstring_checker/html_doc_generator.py
docstring_checker/code_inspection/__init__.py
docstring_checker/code_inspection/base_loader.py
docstring_checker/code_inspection/doc_format.py
docstring_checker/code_inspection/doc_format_enum.py
docstring_checker/code_inspection/docstring_data_collector.py
docstring_checker/code_inspection/docstring_tag_enum.py
docstring_checker/code_inspection/inspector.py
docstring_checker/code_inspection/type_checker.py
docstring_checker/code_inspection/loaders/__init__.py
docstring_checker/code_inspection/loaders/additional_classes_loader.py
docstring_checker/code_inspection/loaders/base_module_loader.py
docstring_checker/code_inspection/loaders/class_loader.py
docstring_checker/code_inspection/loaders/function_loader.py
docstring_checker/code_inspection/loaders/method_loader.py
docstring_checker/code_inspection/loaders/module_loader.py
docstring_checker/code_inspection/loaders/property_loader.py
docstring_checker/data/img/expand.png
docstring_checker/data/img/gremlin.png
docstring_checker/data/img/reduce.png
docstring_checker/data/templates/default_css.css
docstring_checker/data/templates/default_front_page.tpt
docstring_checker/data/templates/default_index.tpt
docstring_checker/data/templates/default_module.tpt
docstring_checker-1.2.data/data/data/img/expand.png
docstring_checker-1.2.data/data/data/img/gremlin.png
docstring_checker-1.2.data/data/data/img/reduce.png
docstring_checker-1.2.data/data/data/templates/default_css.css
docstring_checker-1.2.data/data/data/templates/default_front_page.tpt
docstring_checker-1.2.data/data/data/templates/default_index.tpt
docstring_checker-1.2.data/data/data/templates/default_module.tpt
docstring_checker-1.2.dist-info/METADATA
docstring_checker-1.2.dist-info/WHEEL
docstring_checker-1.2.dist-info/top_level.txt
docstring_checker-1.2.dist-info/RECORD
