Metadata-Version: 2.1
Name: docstring-checker
Version: 1.2
Summary: package to inspect docstrings of a project and generate HTML doc
Author: Marc MALBERT
Author-email: eldrad-59@hotmail.fr
Classifier: Programming Language :: Python :: 3
Classifier: Development Status :: 5 - Production/Stable
Classifier: Natural Language :: English
Classifier: Operating System :: OS Independent
